treex/__init__.py
treex/contexts.py
treex/key_seq.py
treex/losses/__init__.py
treex/losses/cosine_similarity.py
treex/losses/crossentropy.py
treex/losses/huber.py
treex/losses/loss.py
treex/losses/mean_absolute_error.py
treex/losses/mean_absolute_percentage_error.py
treex/losses/mean_squared_error.py
treex/losses/mean_squared_logarithmic_error.py
treex/metrics/__init__.py
treex/metrics/accuracy.py
treex/metrics/loss_and_logs.py
treex/metrics/losses.py
treex/metrics/mean.py
treex/metrics/mean_absolute_error.py
treex/metrics/mean_square_error.py
treex/metrics/metric.py
treex/metrics/metrics.py
treex/metrics/old/accuracy.py
treex/metrics/reduce.py
treex/metrics/tm_port/__init__.py
treex/metrics/tm_port/classification/__init__.py
treex/metrics/tm_port/classification/accuracy.py
treex/metrics/tm_port/classification/stat_scores.py
treex/metrics/tm_port/functional/__init__.py
treex/metrics/tm_port/functional/classification/__init__.py
treex/metrics/tm_port/functional/classification/accuracy.py
treex/metrics/tm_port/functional/classification/stat_scores.py
treex/metrics/tm_port/utilities/__init__.py
treex/metrics/tm_port/utilities/checks.py
treex/metrics/tm_port/utilities/data.py
treex/metrics/tm_port/utilities/distributed.py
treex/metrics/tm_port/utilities/enums.py
treex/metrics/tm_port/utilities/exceptions.py
treex/metrics/tm_port/utilities/imports.py
treex/metrics/tm_port/utilities/prints.py
treex/metrics/utils.py
treex/module.py
treex/nn/__init__.py
treex/nn/conv.py
treex/nn/dropout.py
treex/nn/embed.py
treex/nn/flatten.py
treex/nn/flax_module.py
treex/nn/haiku_module.py
treex/nn/linear.py
treex/nn/mlp.py
treex/nn/norm.py
treex/nn/recurrent.py
treex/nn/sequential.py
treex/optimizer.py
treex/regularizers/__init__.py
treex/regularizers/l1l2.py
treex/treex.py
treex/types.py
treex/utils.py
treex-0.6.12.dist-info/LICENSE
treex-0.6.12.dist-info/WHEEL
treex-0.6.12.dist-info/METADATA
treex-0.6.12.dist-info/RECORD
