Metadata-Version: 2.1
Name: treex
Version: 0.6.12
Summary: 
Home-page: https://cgarciae.github.io/treex
License: MIT
Author: Cristian Garcia
Author-email: cgarcia.e88@gmail.com
Requires-Python: >=3.7,<3.11
Classifier: License :: OSI Approved :: MIT License
Classifier: Programming Language :: Python :: 3
Classifier: Programming Language :: Python :: 3.7
Classifier: Programming Language :: Python :: 3.8
Classifier: Programming Language :: Python :: 3.9
Classifier: Programming Language :: Python :: 3.10
Requires-Dist: PyYAML (>=6.0)
Requires-Dist: certifi (>=2021.10.8)
Requires-Dist: einops (>=0.4.0)
Requires-Dist: flax (>=0.4.0)
Requires-Dist: optax (>=0.1.1)
Requires-Dist: rich (>=11.2.0)
Requires-Dist: treeo (>=0.0.10,<0.0.11)
Project-URL: Repository, https://github.com/cgarciae/treex
